discord_snowflake/__init__.py
discord_snowflake/snowflake.py
discord_snowflake-0.0.1.dist-info/METADATA
discord_snowflake-0.0.1.dist-info/WHEEL
discord_snowflake-0.0.1.dist-info/top_level.txt
discord_snowflake-0.0.1.dist-info/RECORD
