Metadata-Version: 2.1
Name: discord-snowflake
Version: 0.0.1
Summary: ''
Home-page: https://github.com/Fadix47/faginator
Author: Fadix Meier
Author-email: fadix18123@gmail.com
Classifier: Programming Language :: Python :: 3
Classifier: License :: OSI Approved :: MIT License
Classifier: Operating System :: OS Independent
Requires-Python: >=3.6
